cycode/__init__.py
cycode/__main__.py
cycode/cli/__init__.py
cycode/cli/app.py
cycode/cli/apps/__init__.py
cycode/cli/apps/ai_guardrails/__init__.py
cycode/cli/apps/ai_guardrails/command_utils.py
cycode/cli/apps/ai_guardrails/consts.py
cycode/cli/apps/ai_guardrails/hooks_manager.py
cycode/cli/apps/ai_guardrails/install_command.py
cycode/cli/apps/ai_guardrails/scan/__init__.py
cycode/cli/apps/ai_guardrails/scan/consts.py
cycode/cli/apps/ai_guardrails/scan/handlers.py
cycode/cli/apps/ai_guardrails/scan/payload.py
cycode/cli/apps/ai_guardrails/scan/policy.py
cycode/cli/apps/ai_guardrails/scan/response_builders.py
cycode/cli/apps/ai_guardrails/scan/scan_command.py
cycode/cli/apps/ai_guardrails/scan/types.py
cycode/cli/apps/ai_guardrails/scan/utils.py
cycode/cli/apps/ai_guardrails/status_command.py
cycode/cli/apps/ai_guardrails/uninstall_command.py
cycode/cli/apps/ai_remediation/__init__.py
cycode/cli/apps/ai_remediation/ai_remediation_command.py
cycode/cli/apps/ai_remediation/apply_fix.py
cycode/cli/apps/ai_remediation/print_remediation.py
cycode/cli/apps/auth/__init__.py
cycode/cli/apps/auth/auth_command.py
cycode/cli/apps/auth/auth_common.py
cycode/cli/apps/auth/auth_manager.py
cycode/cli/apps/auth/models.py
cycode/cli/apps/configure/__init__.py
cycode/cli/apps/configure/configure_command.py
cycode/cli/apps/configure/consts.py
cycode/cli/apps/configure/messages.py
cycode/cli/apps/configure/prompts.py
cycode/cli/apps/ignore/__init__.py
cycode/cli/apps/ignore/ignore_command.py
cycode/cli/apps/mcp/__init__.py
cycode/cli/apps/mcp/mcp_command.py
cycode/cli/apps/report/__init__.py
cycode/cli/apps/report/report_command.py
cycode/cli/apps/report/sbom/__init__.py
cycode/cli/apps/report/sbom/common.py
cycode/cli/apps/report/sbom/path/__init__.py
cycode/cli/apps/report/sbom/path/path_command.py
cycode/cli/apps/report/sbom/repository_url/__init__.py
cycode/cli/apps/report/sbom/repository_url/repository_url_command.py
cycode/cli/apps/report/sbom/sbom_command.py
cycode-3.9.0.dist-info/METADATA
cycode-3.9.0.dist-info/WHEEL
cycode-3.9.0.dist-info/entry_points.txt
cycode-3.9.0.dist-info/licenses/LICENCE
cycode-3.9.0.dist-info/RECORD
