Metadata-Version: 2.4
Name: cycode
Version: 3.9.0
Summary: Boost security in your dev lifecycle via SAST, SCA, Secrets & IaC scanning.
License-Expression: MIT
License-File: LICENCE
Keywords: secret-scan,cycode,devops,token,secret,security,code
Author: Cycode
Author-email: support@cycode.com
Requires-Python: >=3.9
Classifier: Development Status :: 5 - Production/Stable
Classifier: Environment :: Console
Classifier: Natural Language :: English
Classifier: Operating System :: OS Independent
Classifier: Programming Language :: Python
Classifier: Programming Language :: Python :: 3 :: Only
Classifier: Programming Language :: Python :: 3.9
Classifier: Programming Language :: Python :: 3.10
Classifier: Programming Language :: Python :: 3.11
Classifier: Programming Language :: Python :: 3.12
Classifier: Programming Language :: Python :: 3.13
Classifier: Programming Language :: Python :: 3.14
Requires-Dist: arrow (>=1.0.0,<1.4.0)
Requires-Dist: binaryornot (>=0.4.4,<0.5.0)
Requires-Dist: click (>=8.1.0,<8.2.0)
Requires-Dist: colorama (>=0.4.3,<0.5.0)
Requires-Dist: gitpython (>=3.1.30,<3.2.0)
Requires-Dist: marshmallow (>=3.15.0,<3.23.0)
Requires-Dist: mcp (>=1.9.3,<2.0.0) ; python_version >= "3.10"
Requires-Dist: patch-ng (==1.18.1)
Requires-Dist: pathvalidate (>=3.3.1,<4.0.0)
Requires-Dist: pydantic (>=2.11.5,<3.0.0)
Requires-Dist: pyjwt (>=2.8.0,<3.0)
Requires-Dist: pyyaml (>=6.0,<7.0)
Requires-Dist: requests (>=2.32.4,<3.0)
Requires-Dist: rich (>=13.9.4,<14)
Requires-Dist: sentry-sdk (>=2.8.0,<3.0)
Requires-Dist: tenacity (>=9.0.0,<9.1.0)
Requires-Dist: typer (>=0.15.3,<0.16.0)
Requires-Dist: urllib3 (==1.26.19)
Project-URL: Repository, https://github.com/cycodehq/cycode-cli
